README.md
setup.cfg
setup.py
biva/__init__.py
biva/datasets/__init__.py
biva/datasets/binmnist.py
biva/datasets/cifar10.py
biva/evaluation/__init__.py
biva/evaluation/freebits.py
biva/evaluation/vi.py
biva/layers/__init__.py
biva/layers/block.py
biva/layers/convolution.py
biva/layers/linear.py
biva/model/__init__.py
biva/model/architectures.py
biva/model/deepvae.py
biva/model/stage.py
biva/model/stochastic.py
biva/model/utils.py
biva/utils/__init__.py
biva/utils/discretized_mixture_logits.py
biva/utils/logging.py
biva/utils/ops.py
biva/utils/restore.py
biva/utils/utils.py
biva_pytorch.egg-info/PKG-INFO
biva_pytorch.egg-info/SOURCES.txt
biva_pytorch.egg-info/dependency_links.txt
biva_pytorch.egg-info/requires.txt
biva_pytorch.egg-info/top_level.txt