Metadata-Version: 2.1
Name: biva-pytorch
Version: 0.1.4
Summary: Official PyTorch BIVA implementation (BIVA: A Very Deep Hierarchy of Latent Variables for Generative Modeling)
Home-page: https://github.com/vlievin/biva-pytorch
Author: Valentin Lievin
Author-email: valentin.lievin@gmail.com
License: UNKNOWN
Platform: UNKNOWN
Classifier: Programming Language :: Python :: 3
Classifier: License :: OSI Approved :: MIT License
Classifier: Operating System :: OS Independent
